{
 "updated": "2026-07-18T14:13:39.181Z",
 "moments": [
  {
   "id": "open-championship-2026",
   "off": 0,
   "type": "sport",
   "hot": true,
   "title": "The Open Championship concludes",
   "blurb": "The world's best golfers compete in the final rounds of the 154th Open Championship at Royal Birkdale, with the winner crowned on Sunday.",
   "source": {
    "l": "Olympics.com",
    "u": "https://olympics.com/en/news/the-open-championship-2026-schedule-scores-royal-birkdale"
   },
   "fits": [
    {
     "g": "nation-network",
     "sub": ""
    },
    {
     "g": "nation-network",
     "sub": "Nation Radio London"
    },
    {
     "g": "nation-network",
     "sub": "Nation Radio South"
    },
    {
     "g": "nation-network",
     "sub": "Nation Radio Westcountry"
    },
    {
     "g": "nation-network",
     "sub": "Nation Radio Yorkshire"
    }
   ],
   "angles": [
    {
     "name": "Moving Day",
     "for": "",
     "copy": "It's moving day at Royal Birkdale! Who's making a charge on the leaderboard at The Open today?",
     "channels": [
      "instagram",
      "facebook",
      "x",
      "tiktok",
      "threads"
     ],
     "time": "10:00",
     "tags": [
      "#TheOpen"
     ]
    },
    {
     "name": "Final Day Anticipation",
     "for": "",
     "copy": "The Claret Jug is within touching distance for some. Who do you want to see lift The Open trophy tomorrow?",
     "channels": [
      "instagram",
      "facebook",
      "x",
      "threads"
     ],
     "time": "16:00",
     "tags": [
      "#RoyalBirkdale"
     ]
    }
   ]
  },
  {
   "id": "splendour-festival-final-year",
   "off": 0,
   "type": "gig",
   "hot": true,
   "title": "Splendour Festival's final year",
   "blurb": "Nottingham's Splendour Festival is celebrating its 18th and final year today and tomorrow at Wollaton Hall & Deer Park.",
   "source": {
    "l": "Splendour Festival",
    "u": "https://www.splendourfestival.com/"
   },
   "fits": [
    {
     "g": "nation-network",
     "sub": "Nation Radio Yorkshire"
    },
    {
     "g": "nation-network",
     "sub": ""
    },
    {
     "g": "decades-genres",
     "sub": "Nation Rocks"
    },
    {
     "g": "decades-genres",
     "sub": "Nation Hits"
    },
    {
     "g": "decades-genres",
     "sub": "Nation 90s"
    },
    {
     "g": "decades-genres",
     "sub": "Nation 00s"
    }
   ],
   "angles": [
    {
     "name": "Final Year Sadness",
     "for": "",
     "copy": "Sad news for Nottingham's festival scene as Splendour wraps up its final ever edition this weekend. What's your favourite Splendour memory?",
     "channels": [
      "instagram",
      "facebook",
      "x",
      "threads"
     ],
     "time": "11:00",
     "tags": [
      "#SplendourFestival"
     ]
    },
    {
     "name": "Live from Splendour",
     "for": "",
     "copy": "The last dance at Splendour Festival is happening right now in Nottingham! Who's there sending it off in style?",
     "channels": [
      "instagram",
      "facebook",
      "x",
      "tiktok",
      "threads"
     ],
     "time": "15:00",
     "tags": [
      "#Nottingham"
     ]
    }
   ]
  },
  {
   "id": "love-island-uk-s13",
   "off": 0,
   "type": "tv",
   "hot": true,
   "title": "Love Island UK continues",
   "blurb": "The 13th series of Love Island UK continues nightly, with new islanders entering the villa and relationships constantly shifting.",
   "source": {
    "l": "ITV",
    "u": "https://www.itv.com/loveisland"
   },
   "fits": [
    {
     "g": "nation-network",
     "sub": ""
    },
    {
     "g": "decades-genres",
     "sub": "Nation Hits"
    }
   ],
   "angles": [
    {
     "name": "Recoupling Drama",
     "for": "",
     "copy": "Another day, another recoupling drama in the Love Island villa. Who are you rooting for to go the distance?",
     "channels": [
      "instagram",
      "facebook",
      "x",
      "tiktok",
      "threads"
     ],
     "time": "19:00",
     "tags": [
      "#LoveIslandUK"
     ]
    },
    {
     "name": "New Bombshells",
     "for": "",
     "copy": "Has Love Island found its most dramatic bombshells yet this series? Catch up on all the villa antics.",
     "channels": [
      "instagram",
      "facebook",
      "x",
      "tiktok",
      "threads"
     ],
     "time": "14:00",
     "tags": [
      "#ITV2"
     ]
    }
   ]
  },
  {
   "id": "ann-droid-diane-morgan",
   "off": 0,
   "type": "tv",
   "hot": true,
   "title": "Diane Morgan's 'Ann Droid'",
   "blurb": "Diane Morgan's new comedy series 'Ann Droid', set in 2029 and featuring her as a robot companion, premiered this week on BBC One and iPlayer.",
   "source": {
    "l": "BBC",
    "u": "https://www.bbc.co.uk/iplayer/episodes/m001w09y/ann-droid"
   },
   "fits": [
    {
     "g": "nation-network",
     "sub": ""
    }
   ],
   "angles": [
    {
     "name": "Comedy Gold",
     "for": "",
     "copy": "Diane Morgan as a robot? Yes please! 'Ann Droid' is the new comedy everyone's talking about on BBC iPlayer.",
     "channels": [
      "instagram",
      "facebook",
      "x",
      "threads"
     ],
     "time": "12:00",
     "tags": [
      "#AnnDroid"
     ]
    },
    {
     "name": "Must-Watch TV",
     "for": "",
     "copy": "New TV alert! If you loved 'Motherland', Diane Morgan's 'Ann Droid' is your next must-watch on the BBC.",
     "channels": [
      "instagram",
      "facebook",
      "x",
      "threads"
     ],
     "time": "17:00",
     "tags": [
      "#BBCiPlayer"
     ]
    }
   ]
  },
  {
   "id": "commonwealth-games-glasgow-2026",
   "off": 5,
   "type": "sport",
   "hot": true,
   "title": "Glasgow hosts Commonwealth Games",
   "blurb": "The 2026 Commonwealth Games open in Glasgow next week, with the opening ceremony on July 23rd and athletics starting on July 27th.",
   "source": {
    "l": "Glasgow 2026",
    "u": "https://www.glasgow2026.com/"
   },
   "fits": [
    {
     "g": "nation-network",
     "sub": ""
    },
    {
     "g": "nation-network",
     "sub": "Nation Radio Scotland"
    }
   ],
   "angles": [
    {
     "name": "Games Countdown",
     "for": "",
     "copy": "Glasgow is gearing up to host the Commonwealth Games! The opening ceremony kicks off next Thursday, bringing the world to Scotland.",
     "channels": [
      "instagram",
      "facebook",
      "x",
      "threads"
     ],
     "time": "09:00",
     "tags": [
      "#Glasgow2026"
     ]
    },
    {
     "name": "Athletics Excitement",
     "for": "",
     "copy": "Get ready for world-class sport! The Commonwealth Games begin in Glasgow next week, with athletics hitting the track from July 27th.",
     "channels": [
      "instagram",
      "facebook",
      "x",
      "threads"
     ],
     "time": "14:00",
     "tags": [
      "#CommonwealthGames"
     ]
    }
   ]
  },
  {
   "id": "latitude-festival-2026",
   "off": 5,
   "type": "gig",
   "hot": true,
   "title": "Latitude Festival returns",
   "blurb": "Latitude Festival takes over Henham Park in Suffolk from July 23rd-26th, featuring headliners David Byrne, Teddy Swims, and Lewis Capaldi.",
   "source": {
    "l": "Latitude Festival",
    "u": "https://www.latitudefestival.com/"
   },
   "fits": [
    {
     "g": "nation-network",
     "sub": "Nation Radio Suffolk"
    },
    {
     "g": "nation-network",
     "sub": ""
    },
    {
     "g": "decades-genres",
     "sub": "Nation Rocks"
    },
    {
     "g": "decades-genres",
     "sub": "Nation Hits"
    },
    {
     "g": "decades-genres",
     "sub": "Nation 80s"
    },
    {
     "g": "decades-genres",
     "sub": "Nation 90s"
    },
    {
     "g": "decades-genres",
     "sub": "Nation 00s"
    }
   ],
   "angles": [
    {
     "name": "Festival Lineup",
     "for": "",
     "copy": "Who's heading to Latitude next week? David Byrne, Teddy Swims & Lewis Capaldi are set to headline in Suffolk!",
     "channels": [
      "instagram",
      "facebook",
      "x",
      "threads"
     ],
     "time": "10:00",
     "tags": [
      "#LatitudeFestival"
     ]
    },
    {
     "name": "Festival Vibes",
     "for": "",
     "copy": "Festival vibes incoming! Latitude is back in Henham Park from Thursday. What acts are you most excited to see?",
     "channels": [
      "instagram",
      "facebook",
      "x",
      "tiktok",
      "threads"
     ],
     "time": "16:00",
     "tags": [
      "#Suffolk"
     ]
    }
   ]
  },
  {
   "id": "together-again-festival-2026",
   "off": 6,
   "type": "gig",
   "hot": true,
   "title": "Together Again Festival",
   "blurb": "The Together Again Festival runs from July 24th-26th at Bolesworth Castle, Cheshire, promising a mix of dance, pop anthems and UK garage.",
   "source": {
    "l": "Together Again Festival",
    "u": "https://togetheragainfestival.co.uk/"
   },
   "fits": [
    {
     "g": "decades-genres",
     "sub": "Nation Dance"
    },
    {
     "g": "decades-genres",
     "sub": "Nation Hits"
    },
    {
     "g": "decades-genres",
     "sub": "Nation 90s"
    },
    {
     "g": "decades-genres",
     "sub": "Nation 00s"
    },
    {
     "g": "nation-network",
     "sub": ""
    },
    {
     "g": "nation-network",
     "sub": "Nation Radio London"
    },
    {
     "g": "nation-network",
     "sub": "Nation Radio Yorkshire"
    }
   ],
   "angles": [
    {
     "name": "Throwback Party",
     "for": "",
     "copy": "Ready for a throwback? Together Again Festival in Cheshire has your dose of dance, pop anthems & UK garage next weekend!",
     "channels": [
      "instagram",
      "facebook",
      "x",
      "threads"
     ],
     "time": "11:00",
     "tags": [
      "#TogetherAgain"
     ]
    },
    {
     "name": "Cheshire Festival",
     "for": "",
     "copy": "Bolesworth Castle is about to get lively! Together Again Festival brings the party next weekend. Who's in?",
     "channels": [
      "instagram",
      "facebook",
      "x",
      "tiktok",
      "threads"
     ],
     "time": "15:00",
     "tags": [
      "#CheshireEvents"
     ]
    }
   ]
  },
  {
   "id": "big-love-festival-wales",
   "off": 0,
   "type": "gig",
   "hot": true,
   "title": "Big Love Festival in South Wales",
   "blurb": "South Wales is celebrating 10 years of Big Love, a small music festival set in the countryside this July.",
   "source": {
    "l": "Big Love Festival",
    "u": "https://biglovefestival.co.uk/"
   },
   "fits": [
    {
     "g": "welsh-local",
     "sub": ""
    },
    {
     "g": "dragon",
     "sub": ""
    },
    {
     "g": "nation-network",
     "sub": ""
    },
    {
     "g": "decades-genres",
     "sub": "Nation Rocks"
    },
    {
     "g": "decades-genres",
     "sub": "Nation Hits"
    }
   ],
   "angles": [
    {
     "name": "10th Anniversary",
     "for": "",
     "copy": "Happy 10th Birthday to Big Love Festival in South Wales! Who's enjoying the celebrations this month?",
     "channels": [
      "instagram",
      "facebook",
      "x",
      "threads"
     ],
     "time": "13:00",
     "tags": [
      "#BigLoveFestival"
     ]
    },
    {
     "name": "Welsh Festival Fun",
     "for": "",
     "copy": "Small festival, big heart! Big Love Festival is bringing the tunes to the Welsh countryside this July. Are you there?",
     "channels": [
      "instagram",
      "facebook",
      "x",
      "tiktok",
      "threads"
     ],
     "time": "17:00",
     "tags": [
      "#WalesMusic"
     ]
    }
   ]
  },
  {
   "id": "george-clinton-85th-birthday",
   "off": 4,
   "type": "birthday",
   "hot": true,
   "title": "Happy 85th to George Clinton",
   "blurb": "Funk legend George Clinton, leader of Parliament-Funkadelic, celebrates his 85th birthday on July 22nd.",
   "source": {
    "l": "AP News",
    "u": "https://apnews.com/article/celebrity-birthdays-benedict-cumberbatch-john-leguizamo-a11354044b7f830c24237199186419d1"
   },
   "fits": [
    {
     "g": "decades-genres",
     "sub": "Nation Classic Hits"
    },
    {
     "g": "decades-genres",
     "sub": "Nation Easy"
    },
    {
     "g": "decades-genres",
     "sub": "Nation 70s"
    }
   ],
   "angles": [
    {
     "name": "Funk Godfather",
     "for": "",
     "copy": "Get ready to funk it up! The legendary George Clinton turns 85 this Wednesday. What's your favourite P-Funk track?",
     "channels": [
      "instagram",
      "facebook",
      "x",
      "threads"
     ],
     "time": "09:00",
     "tags": [
      "#GeorgeClinton"
     ]
    },
    {
     "name": "Music Icon",
     "for": "",
     "copy": "Happy 85th birthday to the Godfather of Funk, George Clinton! His influence is still massive.",
     "channels": [
      "instagram",
      "facebook",
      "x",
      "threads"
     ],
     "time": "14:00",
     "tags": [
      "#ParliamentFunkadelic"
     ]
    }
   ]
  },
  {
   "id": "don-henley-79th-birthday",
   "off": 4,
   "type": "birthday",
   "hot": true,
   "title": "Happy 79th to Don Henley",
   "blurb": "Eagles co-founder and drumming legend Don Henley celebrates his 79th birthday on July 22nd.",
   "source": {
    "l": "AP News",
    "u": "https://apnews.com/article/celebrity-birthdays-benedict-cumberbatch-john-leguizamo-a11354044b7f830c24237199186419d1"
   },
   "fits": [
    {
     "g": "decades-genres",
     "sub": "Nation 70s"
    },
    {
     "g": "decades-genres",
     "sub": "Nation 80s"
    },
    {
     "g": "decades-genres",
     "sub": "Nation Classic Hits"
    },
    {
     "g": "decades-genres",
     "sub": "Nation Rocks"
    }
   ],
   "angles": [
    {
     "name": "Eagles Legend",
     "for": "",
     "copy": "Hotel California and so much more! Happy 79th birthday to Eagles icon Don Henley this Wednesday.",
     "channels": [
      "instagram",
      "facebook",
      "x",
      "threads"
     ],
     "time": "10:00",
     "tags": [
      "#DonHenley"
     ]
    },
    {
     "name": "Vocalist & Drummer",
     "for": "",
     "copy": "Celebrating Don Henley's 79th this week! What's your go-to Eagles track featuring his incredible vocals?",
     "channels": [
      "instagram",
      "facebook",
      "x",
      "threads"
     ],
     "time": "15:00",
     "tags": [
      "#TheEagles"
     ]
    }
   ]
  },
  {
   "id": "carlos-santana-79th-birthday",
   "off": 2,
   "type": "birthday",
   "hot": true,
   "title": "Happy 79th to Carlos Santana",
   "blurb": "Guitar icon Carlos Santana celebrates his 79th birthday on July 20th.",
   "source": {
    "l": "AP News",
    "u": "https://apnews.com/article/celebrity-birthdays-benedict-cumberbatch-john-leguizamo-a11354044b7f830c24237199186419d1"
   },
   "fits": [
    {
     "g": "decades-genres",
     "sub": "Nation 70s"
    },
    {
     "g": "decades-genres",
     "sub": "Nation Classic Hits"
    },
    {
     "g": "decades-genres",
     "sub": "Nation Rocks"
    }
   ],
   "angles": [
    {
     "name": "Guitar Legend",
     "for": "",
     "copy": "Smooth guitar and timeless riffs! Carlos Santana turns 79 on Monday. What's your favourite Santana classic?",
     "channels": [
      "instagram",
      "facebook",
      "x",
      "threads"
     ],
     "time": "09:00",
     "tags": [
      "#CarlosSantana"
     ]
    },
    {
     "name": "Still Rocking",
     "for": "",
     "copy": "Happy birthday to the legendary Carlos Santana, turning 79 this Monday. Still rocking after all these years!",
     "channels": [
      "instagram",
      "facebook",
      "x",
      "threads"
     ],
     "time": "14:00",
     "tags": [
      "#Santana"
     ]
    }
   ]
  },
  {
   "id": "paul-cook-70th-birthday",
   "off": 2,
   "type": "birthday",
   "hot": true,
   "title": "Happy 70th to Paul Cook",
   "blurb": "Sex Pistols drummer Paul Cook, a punk rock icon, celebrates his 70th birthday on July 20th.",
   "source": {
    "l": "AP News",
    "u": "https://apnews.com/article/celebrity-birthdays-benedict-cumberbatch-john-leguizamo-a11354044b7f830c24237199186419d1"
   },
   "fits": [
    {
     "g": "decades-genres",
     "sub": "Nation Rocks"
    },
    {
     "g": "decades-genres",
     "sub": "Nation 70s"
    }
   ],
   "angles": [
    {
     "name": "Punk Icon",
     "for": "",
     "copy": "God Save The Queen! Sex Pistols drummer Paul Cook turns 70 on Monday. What's your favourite punk anthem?",
     "channels": [
      "instagram",
      "facebook",
      "x",
      "threads"
     ],
     "time": "10:00",
     "tags": [
      "#PaulCook"
     ]
    },
    {
     "name": "Influential Drummer",
     "for": "",
     "copy": "Happy 70th birthday to punk legend Paul Cook! Still influencing bands today.",
     "channels": [
      "instagram",
      "facebook",
      "x",
      "threads"
     ],
     "time": "15:00",
     "tags": [
      "#SexPistols"
     ]
    }
   ]
  },
  {
   "id": "stone-gossard-60th-birthday",
   "off": 2,
   "type": "birthday",
   "hot": true,
   "title": "Happy 60th to Stone Gossard",
   "blurb": "Pearl Jam guitarist and co-founder Stone Gossard celebrates his 60th birthday on July 20th.",
   "source": {
    "l": "AP News",
    "u": "https://apnews.com/article/celebrity-birthdays-benedict-cumberbatch-john-leguizamo-a11354044b7f830c24237199186419d1"
   },
   "fits": [
    {
     "g": "decades-genres",
     "sub": "Nation Rocks"
    },
    {
     "g": "decades-genres",
     "sub": "Nation 90s"
    }
   ],
   "angles": [
    {
     "name": "Grunge Pioneer",
     "for": "",
     "copy": "From grunge pioneers to rock legends! Happy 60th birthday to Pearl Jam's Stone Gossard this Monday.",
     "channels": [
      "instagram",
      "facebook",
      "x",
      "threads"
     ],
     "time": "11:00",
     "tags": [
      "#StoneGossard"
     ]
    },
    {
     "name": "Pearl Jam Tracks",
     "for": "",
     "copy": "Celebrating Stone Gossard's 60th! What's your all-time favourite Pearl Jam track?",
     "channels": [
      "instagram",
      "facebook",
      "x",
      "threads"
     ],
     "time": "16:00",
     "tags": [
      "#PearlJam"
     ]
    }
   ]
  },
  {
   "id": "david-essex-79th-birthday",
   "off": 5,
   "type": "birthday",
   "hot": true,
   "title": "Happy 79th to David Essex",
   "blurb": "British singer, songwriter and actor David Essex, known for hits like \"Gonna Make You A Star\", turns 79 on July 23rd.",
   "source": {
    "l": "AP News",
    "u": "https://apnews.com/article/celebrity-birthdays-benedict-cumberbatch-john-leguizamo-a11354044b7f830c24237199186419d1"
   },
   "fits": [
    {
     "g": "decades-genres",
     "sub": "Nation 70s"
    },
    {
     "g": "decades-genres",
     "sub": "Nation Classic Hits"
    },
    {
     "g": "decades-genres",
     "sub": "Nation Easy"
    }
   ],
   "angles": [
    {
     "name": "British Icon",
     "for": "",
     "copy": "Gonna make you a star! Happy 79th birthday to the fantastic David Essex this Thursday.",
     "channels": [
      "instagram",
      "facebook",
      "x",
      "threads"
     ],
     "time": "09:00",
     "tags": [
      "#DavidEssex"
     ]
    },
    {
     "name": "Classic Hits",
     "for": "",
     "copy": "Celebrating the career of David Essex, who turns 79 this week. What's your favourite song by the British icon?",
     "channels": [
      "instagram",
      "facebook",
      "x",
      "threads"
     ],
     "time": "14:00",
     "tags": [
      "#70sMusic"
     ]
    }
   ]
  },
  {
   "id": "martin-gore-65th-birthday",
   "off": 5,
   "type": "birthday",
   "hot": true,
   "title": "Happy 65th to Martin Gore",
   "blurb": "Depeche Mode co-founder and primary songwriter Martin Gore celebrates his 65th birthday on July 23rd.",
   "source": {
    "l": "AP News",
    "u": "https://apnews.com/article/celebrity-birthdays-benedict-cumberbatch-john-leguizamo-a11354044b7f830c24237199186419d1"
   },
   "fits": [
    {
     "g": "decades-genres",
     "sub": "Nation 80s"
    },
    {
     "g": "decades-genres",
     "sub": "Nation Dance"
    },
    {
     "g": "decades-genres",
     "sub": "Nation Rocks"
    }
   ],
   "angles": [
    {
     "name": "Depeche Mode Mastermind",
     "for": "",
     "copy": "Just Can't Get Enough of Depeche Mode? Happy 65th birthday to the brilliant Martin Gore this Thursday!",
     "channels": [
      "instagram",
      "facebook",
      "x",
      "threads"
     ],
     "time": "10:00",
     "tags": [
      "#MartinGore"
     ]
    },
    {
     "name": "Synth Pop Legend",
     "for": "",
     "copy": "Celebrating Martin Gore's 65th! The man behind so many Depeche Mode classics.",
     "channels": [
      "instagram",
      "facebook",
      "x",
      "threads"
     ],
     "time": "15:00",
     "tags": [
      "#DepecheMode"
     ]
    }
   ]
  },
  {
   "id": "verdine-white-75th-birthday",
   "off": 7,
   "type": "birthday",
   "hot": true,
   "title": "Happy 75th to Verdine White",
   "blurb": "Earth, Wind & Fire bassist Verdine White, known for his energetic stage presence, celebrates his 75th birthday on July 25th.",
   "source": {
    "l": "AP News",
    "u": "https://apnews.com/article/celebrity-birthdays-benedict-cumberbatch-john-leguizamo-a11354044b7f830c24237199186419d1"
   },
   "fits": [
    {
     "g": "decades-genres",
     "sub": "Nation 70s"
    },
    {
     "g": "decades-genres",
     "sub": "Nation Classic Hits"
    },
    {
     "g": "decades-genres",
     "sub": "Nation Easy"
    },
    {
     "g": "decades-genres",
     "sub": "Nation Dance"
    }
   ],
   "angles": [
    {
     "name": "Funk Powerhouse",
     "for": "",
     "copy": "Shining Star! Earth, Wind & Fire's incredible bassist Verdine White turns 75 this Saturday. What's your favourite EWF jam?",
     "channels": [
      "instagram",
      "facebook",
      "x",
      "threads"
     ],
     "time": "09:00",
     "tags": [
      "#VerdineWhite"
     ]
    },
    {
     "name": "EWF Energy",
     "for": "",
     "copy": "Happy 75th birthday to the one and only Verdine White! Still bringing the funk and energy.",
     "channels": [
      "instagram",
      "facebook",
      "x",
      "threads"
     ],
     "time": "14:00",
     "tags": [
      "#EarthWindAndFire"
     ]
    }
   ]
  },
  {
   "id": "mick-jagger-83rd-birthday",
   "off": 8,
   "type": "birthday",
   "hot": true,
   "title": "Happy 83rd to Mick Jagger",
   "blurb": "Rolling Stones frontman and rock icon Mick Jagger celebrates his 83rd birthday on July 26th.",
   "source": {
    "l": "Famous Birthdays",
    "u": "https://www.famousbirthdays.com/born/07/26"
   },
   "fits": [
    {
     "g": "decades-genres",
     "sub": "Nation 60s"
    },
    {
     "g": "decades-genres",
     "sub": "Nation 70s"
    },
    {
     "g": "decades-genres",
     "sub": "Nation Classic Hits"
    },
    {
     "g": "decades-genres",
     "sub": "Nation Rocks"
    }
   ],
   "angles": [
    {
     "name": "Rock Legend",
     "for": "",
     "copy": "Still got the moves like Jagger! The legendary Mick Jagger turns 83 this Sunday. What's your favourite Stones track?",
     "channels": [
      "instagram",
      "facebook",
      "x",
      "tiktok",
      "threads"
     ],
     "time": "10:00",
     "tags": [
      "#MickJagger"
     ]
    },
    {
     "name": "Ageless Icon",
     "for": "",
     "copy": "Happy 83rd birthday to the incomparable Mick Jagger! A true rock and roll survivor.",
     "channels": [
      "instagram",
      "facebook",
      "x",
      "threads"
     ],
     "time": "15:00",
     "tags": [
      "#RollingStones"
     ]
    }
   ]
  },
  {
   "id": "roger-taylor-77th-birthday",
   "off": 8,
   "type": "birthday",
   "hot": true,
   "title": "Happy 77th to Roger Taylor",
   "blurb": "Queen drummer and songwriter Roger Taylor celebrates his 77th birthday on July 26th.",
   "source": {
    "l": "Famous Birthdays",
    "u": "https://www.famousbirthdays.com/born/07/26"
   },
   "fits": [
    {
     "g": "decades-genres",
     "sub": "Nation 70s"
    },
    {
     "g": "decades-genres",
     "sub": "Nation 80s"
    },
    {
     "g": "decades-genres",
     "sub": "Nation Classic Hits"
    },
    {
     "g": "decades-genres",
     "sub": "Nation Rocks"
    }
   ],
   "angles": [
    {
     "name": "Queen Drummer",
     "for": "",
     "copy": "We Will Rock You! Happy 77th birthday to Queen's legendary drummer Roger Taylor this Sunday.",
     "channels": [
      "instagram",
      "facebook",
      "x",
      "threads"
     ],
     "time": "11:00",
     "tags": [
      "#RogerTaylor"
     ]
    },
    {
     "name": "Songwriter Talent",
     "for": "",
     "copy": "Celebrating the powerhouse behind Queen, Roger Taylor, who turns 77 this weekend. What's your favourite Queen song he wrote or sang lead on?",
     "channels": [
      "instagram",
      "facebook",
      "x",
      "threads"
     ],
     "time": "16:00",
     "tags": [
      "#QueenBand"
     ]
    }
   ]
  },
  {
   "id": "darlene-love-85th-birthday",
   "off": 8,
   "type": "birthday",
   "hot": true,
   "title": "Happy 85th to Darlene Love",
   "blurb": "Legendary singer Darlene Love, known for her powerful vocals and Christmas classic \"Christmas (Baby Please Come Home)\", turns 85 on July 26th.",
   "source": {
    "l": "Famous Birthdays",
    "u": "https://www.famousbirthdays.com/born/07/26"
   },
   "fits": [
    {
     "g": "decades-genres",
     "sub": "Nation 60s"
    },
    {
     "g": "decades-genres",
     "sub": "Nation Classic Hits"
    },
    {
     "g": "decades-genres",
     "sub": "Nation Easy"
    },
    {
     "g": "decades-genres",
     "sub": "Nation Xmas"
    }
   ],
   "angles": [
    {
     "name": "Powerful Vocals",
     "for": "",
     "copy": "A voice that truly shines! Happy 85th birthday to the incredible Darlene Love this Sunday.",
     "channels": [
      "instagram",
      "facebook",
      "x",
      "threads"
     ],
     "time": "12:00",
     "tags": [
      "#DarleneLove"
     ]
    },
    {
     "name": "Timeless Icon",
     "for": "",
     "copy": "Beyond the Christmas classic, Darlene Love is a true icon. Celebrating her 85th this weekend!",
     "channels": [
      "instagram",
      "facebook",
      "x",
      "threads"
     ],
     "time": "17:00",
     "tags": [
      "#SoulSinger"
     ]
    }
   ]
  },
  {
   "id": "taylor-momsen-33rd-birthday",
   "off": 8,
   "type": "birthday",
   "hot": true,
   "title": "Happy 33rd to Taylor Momsen",
   "blurb": "The Pretty Reckless frontwoman Taylor Momsen celebrates her 33rd birthday on July 26th.",
   "source": {
    "l": "Famous Birthdays",
    "u": "https://www.famousbirthdays.com/born/07/26"
   },
   "fits": [
    {
     "g": "decades-genres",
     "sub": "Nation Rocks"
    },
    {
     "g": "decades-genres",
     "sub": "Nation Hits"
    }
   ],
   "angles": [
    {
     "name": "Rock Frontwoman",
     "for": "",
     "copy": "Make Me Wanna Die! Happy 33rd birthday to The Pretty Reckless's fierce frontwoman Taylor Momsen this Sunday.",
     "channels": [
      "instagram",
      "facebook",
      "x",
      "threads"
     ],
     "time": "13:00",
     "tags": [
      "#TaylorMomsen"
     ]
    },
    {
     "name": "The Pretty Reckless",
     "for": "",
     "copy": "Celebrating Taylor Momsen's 33rd this weekend! What's your favourite track from The Pretty Reckless?",
     "channels": [
      "instagram",
      "facebook",
      "x",
      "threads"
     ],
     "time": "18:00",
     "tags": [
      "#ThePrettyReckless"
     ]
    }
   ]
  },
  {
   "id": "stormzy-33rd-birthday",
   "off": 8,
   "type": "birthday",
   "hot": true,
   "title": "Happy 33rd to Stormzy",
   "blurb": "Grime superstar Stormzy celebrates his 33rd birthday on July 26th.",
   "source": {
    "l": "Famous Birthdays",
    "u": "https://www.famousbirthdays.com/born/07/26"
   },
   "fits": [
    {
     "g": "decades-genres",
     "sub": "Nation Hits"
    },
    {
     "g": "decades-genres",
     "sub": "Nation Dance"
    }
   ],
   "angles": [
    {
     "name": "Grime King",
     "for": "",
     "copy": "Big Mike is 33! Happy birthday to the one and only Stormzy this Sunday. What's your favourite track from the grime king?",
     "channels": [
      "instagram",
      "facebook",
      "x",
      "tiktok",
      "threads"
     ],
     "time": "14:00",
     "tags": [
      "#Stormzy"
     ]
    },
    {
     "name": "Music Scene Impact",
     "for": "",
     "copy": "Celebrating Stormzy's 33rd this weekend! Still making waves across the music scene.",
     "channels": [
      "instagram",
      "facebook",
      "x",
      "threads"
     ],
     "time": "19:00",
     "tags": [
      "#GrimeMusic"
     ]
    }
   ]
  }
 ],
 "source": "gemini"
}